{
  "version": 1,
  "updated_at": "2026-05-07T09:56:45Z",
  "updated_by": "Pagayo",
  "repos": {
    "pagayo-storefront": {
      "staging_sha": "df782b18a063402bb4789c8eec0dc0fbdd2481ff",
      "verified_at": "2026-05-07T09:56:45Z"
    },
    "pagayo-api-stack": {
      "staging_sha": "fc1a59f4220b5a56351fbd1c4d15f99d1723fda0",
      "verified_at": "2026-05-06T17:30:07Z"
    },
    "pagayo-edge": {
      "staging_sha": "ae0e8eca35f9ca5e7b5ff07c2a6f40e4ed5737a4",
      "verified_at": "2026-04-26T11:46:01Z"
    },
    "pagayo-workflows": {
      "staging_sha": "acdd46b2ce73c03a5b2e9bd8a461dd2a860ac32d",
      "verified_at": "2026-04-27T11:55:38Z"
    },
    "pagayo-schema": {
      "staging_sha": null,
      "verified_at": null
    },
    "pagayo-config": {
      "staging_sha": null,
      "verified_at": null
    },
    "pagayo-design": {
      "staging_sha": null,
      "verified_at": null
    },
    "pagayo-marketing": {
      "staging_sha": null,
      "verified_at": null
    },
    "pagayo-cloudflare-proxy": {
      "staging_sha": null,
      "verified_at": null
    },
    "pagayo-maintenance": {
      "staging_sha": null,
      "verified_at": null
    }
  }
}
